mypasswd/__init__.py
mypasswd/mypasswd.py
mypasswd-0.0.2.dist-info/DESCRIPTION.rst
mypasswd-0.0.2.dist-info/METADATA
mypasswd-0.0.2.dist-info/RECORD
mypasswd-0.0.2.dist-info/WHEEL
mypasswd-0.0.2.dist-info/metadata.json
mypasswd-0.0.2.dist-info/top_level.txt
