Metadata-Version: 2.0
Name: mypasswd
Version: 0.0.2
Summary: A simple secure programmer - specific password management tool
Home-page: https://github.com/applesline/mypasswd
Author: liuyaping
Author-email: applesline@163.com
License: UNKNOWN
Platform: UNKNOWN
Classifier: Programming Language :: Python :: 3
Classifier: License :: OSI Approved :: MIT License
Classifier: Operating System :: OS Independent
